README.md
pyproject.toml
setup.cfg
setup.py
django_relations/__init__.py
django_relations/apps.py
django_relations/managers.py
django_relations/models.py
django_relations.egg-info/PKG-INFO
django_relations.egg-info/SOURCES.txt
django_relations.egg-info/dependency_links.txt
django_relations.egg-info/requires.txt
django_relations.egg-info/top_level.txt